{"nodes": [{"id": "c_moya_flutter_lib_core_services_location_service_dart", "label": "location_service.dart", "file_type": "code", "source_file": "C:\\MOYA\\flutter\\lib\\core\\services\\location_service.dart", "source_location": null}, {"id": "c_moya_flutter_lib_core_services_location_service_dart_locationconfig", "label": "LocationConfig", "file_type": "code", "source_file": "C:\\MOYA\\flutter\\lib\\core\\services\\location_service.dart", "source_location": null}, {"id": "c_moya_flutter_lib_core_services_location_service_dart_gpslocationservice", "label": "GpsLocationService", "file_type": "code", "source_file": "C:\\MOYA\\flutter\\lib\\core\\services\\location_service.dart", "source_location": null}, {"id": "c_moya_flutter_lib_core_services_location_service_dart_setsessionid", "label": "setSessionId", "file_type": "code", "source_file": "C:\\MOYA\\flutter\\lib\\core\\services\\location_service.dart", "source_location": null}, {"id": "c_moya_flutter_lib_core_services_location_service_dart_onpositionupdate", "label": "_onPositionUpdate", "file_type": "code", "source_file": "C:\\MOYA\\flutter\\lib\\core\\services\\location_service.dart", "source_location": null}, {"id": "c_moya_flutter_lib_core_services_location_service_dart_setsharingenabled", "label": "setSharingEnabled", "file_type": "code", "source_file": "C:\\MOYA\\flutter\\lib\\core\\services\\location_service.dart", "source_location": null}, {"id": "c_moya_flutter_lib_core_services_location_service_dart_startstatusdetection", "label": "_startStatusDetection", "file_type": "code", "source_file": "C:\\MOYA\\flutter\\lib\\core\\services\\location_service.dart", "source_location": null}, {"id": "c_moya_flutter_lib_core_services_location_service_dart_exception", "label": "Exception", "file_type": "code", "source_file": "C:\\MOYA\\flutter\\lib\\core\\services\\location_service.dart", "source_location": null}, {"id": "c_moya_flutter_lib_core_services_location_service_dart_dispose", "label": "dispose", "file_type": "code", "source_file": "C:\\MOYA\\flutter\\lib\\core\\services\\location_service.dart", "source_location": null}, {"id": "dart_async", "label": "dart:async", "file_type": "code", "source_file": "C:\\MOYA\\flutter\\lib\\core\\services\\location_service.dart", "source_location": null}, {"id": "dart_io", "label": "dart:io", "file_type": "code", "source_file": "C:\\MOYA\\flutter\\lib\\core\\services\\location_service.dart", "source_location": null}, {"id": "package_battery_plus_battery_plus_dart", "label": "package:battery_plus/battery_plus.dart", "file_type": "code", "source_file": "C:\\MOYA\\flutter\\lib\\core\\services\\location_service.dart", "source_location": null}, {"id": "package_flutter_foundation_dart", "label": "package:flutter/foundation.dart", "file_type": "code", "source_file": "C:\\MOYA\\flutter\\lib\\core\\services\\location_service.dart", "source_location": null}, {"id": "package_geolocator_geolocator_dart", "label": "package:geolocator/geolocator.dart", "file_type": "code", "source_file": "C:\\MOYA\\flutter\\lib\\core\\services\\location_service.dart", "source_location": null}, {"id": "permission_lock_dart", "label": "permission_lock.dart", "file_type": "code", "source_file": "C:\\MOYA\\flutter\\lib\\core\\services\\location_service.dart", "source_location": null}, {"id": "socket_service_dart", "label": "socket_service.dart", "file_type": "code", "source_file": "C:\\MOYA\\flutter\\lib\\core\\services\\location_service.dart", "source_location": null}], "edges": [{"source": "c_moya_flutter_lib_core_services_location_service_dart", "target": "c_moya_flutter_lib_core_services_location_service_dart_locationconfig", "relation": "defines", "confidence": "EXTRACTED", "confidence_score": 1.0, "source_file": "C:\\MOYA\\flutter\\lib\\core\\services\\location_service.dart", "source_location": null, "weight": 1.0}, {"source": "c_moya_flutter_lib_core_services_location_service_dart", "target": "c_moya_flutter_lib_core_services_location_service_dart_gpslocationservice", "relation": "defines", "confidence": "EXTRACTED", "confidence_score": 1.0, "source_file": "C:\\MOYA\\flutter\\lib\\core\\services\\location_service.dart", "source_location": null, "weight": 1.0}, {"source": "c_moya_flutter_lib_core_services_location_service_dart", "target": "c_moya_flutter_lib_core_services_location_service_dart_setsessionid", "relation": "defines", "confidence": "EXTRACTED", "confidence_score": 1.0, "source_file": "C:\\MOYA\\flutter\\lib\\core\\services\\location_service.dart", "source_location": null, "weight": 1.0}, {"source": "c_moya_flutter_lib_core_services_location_service_dart", "target": "c_moya_flutter_lib_core_services_location_service_dart_onpositionupdate", "relation": "defines", "confidence": "EXTRACTED", "confidence_score": 1.0, "source_file": "C:\\MOYA\\flutter\\lib\\core\\services\\location_service.dart", "source_location": null, "weight": 1.0}, {"source": "c_moya_flutter_lib_core_services_location_service_dart", "target": "c_moya_flutter_lib_core_services_location_service_dart_setsharingenabled", "relation": "defines", "confidence": "EXTRACTED", "confidence_score": 1.0, "source_file": "C:\\MOYA\\flutter\\lib\\core\\services\\location_service.dart", "source_location": null, "weight": 1.0}, {"source": "c_moya_flutter_lib_core_services_location_service_dart", "target": "c_moya_flutter_lib_core_services_location_service_dart_startstatusdetection", "relation": "defines", "confidence": "EXTRACTED", "confidence_score": 1.0, "source_file": "C:\\MOYA\\flutter\\lib\\core\\services\\location_service.dart", "source_location": null, "weight": 1.0}, {"source": "c_moya_flutter_lib_core_services_location_service_dart", "target": "c_moya_flutter_lib_core_services_location_service_dart_exception", "relation": "defines", "confidence": "EXTRACTED", "confidence_score": 1.0, "source_file": "C:\\MOYA\\flutter\\lib\\core\\services\\location_service.dart", "source_location": null, "weight": 1.0}, {"source": "c_moya_flutter_lib_core_services_location_service_dart", "target": "c_moya_flutter_lib_core_services_location_service_dart_dispose", "relation": "defines", "confidence": "EXTRACTED", "confidence_score": 1.0, "source_file": "C:\\MOYA\\flutter\\lib\\core\\services\\location_service.dart", "source_location": null, "weight": 1.0}, {"source": "c_moya_flutter_lib_core_services_location_service_dart", "target": "dart_async", "relation": "imports", "confidence": "EXTRACTED", "confidence_score": 1.0, "source_file": "C:\\MOYA\\flutter\\lib\\core\\services\\location_service.dart", "source_location": null, "weight": 1.0}, {"source": "c_moya_flutter_lib_core_services_location_service_dart", "target": "dart_io", "relation": "imports", "confidence": "EXTRACTED", "confidence_score": 1.0, "source_file": "C:\\MOYA\\flutter\\lib\\core\\services\\location_service.dart", "source_location": null, "weight": 1.0}, {"source": "c_moya_flutter_lib_core_services_location_service_dart", "target": "package_battery_plus_battery_plus_dart", "relation": "imports", "confidence": "EXTRACTED", "confidence_score": 1.0, "source_file": "C:\\MOYA\\flutter\\lib\\core\\services\\location_service.dart", "source_location": null, "weight": 1.0}, {"source": "c_moya_flutter_lib_core_services_location_service_dart", "target": "package_flutter_foundation_dart", "relation": "imports", "confidence": "EXTRACTED", "confidence_score": 1.0, "source_file": "C:\\MOYA\\flutter\\lib\\core\\services\\location_service.dart", "source_location": null, "weight": 1.0}, {"source": "c_moya_flutter_lib_core_services_location_service_dart", "target": "package_geolocator_geolocator_dart", "relation": "imports", "confidence": "EXTRACTED", "confidence_score": 1.0, "source_file": "C:\\MOYA\\flutter\\lib\\core\\services\\location_service.dart", "source_location": null, "weight": 1.0}, {"source": "c_moya_flutter_lib_core_services_location_service_dart", "target": "permission_lock_dart", "relation": "imports", "confidence": "EXTRACTED", "confidence_score": 1.0, "source_file": "C:\\MOYA\\flutter\\lib\\core\\services\\location_service.dart", "source_location": null, "weight": 1.0}, {"source": "c_moya_flutter_lib_core_services_location_service_dart", "target": "socket_service_dart", "relation": "imports", "confidence": "EXTRACTED", "confidence_score": 1.0, "source_file": "C:\\MOYA\\flutter\\lib\\core\\services\\location_service.dart", "source_location": null, "weight": 1.0}]}