{"nodes": [{"id": "c_moya_flutter_packages_flutter_webrtc_android_src_main_java_com_cloudwebrtc_webrtc_utils_utils_java", "label": "Utils.java", "file_type": "code", "source_file": "C:\\MOYA\\flutter\\packages\\flutter_webrtc\\android\\src\\main\\java\\com\\cloudwebrtc\\webrtc\\utils\\Utils.java", "source_location": "L1"}, {"id": "utils_utils_utils", "label": "Utils", "file_type": "code", "source_file": "C:\\MOYA\\flutter\\packages\\flutter_webrtc\\android\\src\\main\\java\\com\\cloudwebrtc\\webrtc\\utils\\Utils.java", "source_location": "L7"}, {"id": "utils_utils_utils_iceconnectionstatestring", "label": ".iceConnectionStateString()", "file_type": "code", "source_file": "C:\\MOYA\\flutter\\packages\\flutter_webrtc\\android\\src\\main\\java\\com\\cloudwebrtc\\webrtc\\utils\\Utils.java", "source_location": "L9"}, {"id": "utils_utils_utils_icegatheringstatestring", "label": ".iceGatheringStateString()", "file_type": "code", "source_file": "C:\\MOYA\\flutter\\packages\\flutter_webrtc\\android\\src\\main\\java\\com\\cloudwebrtc\\webrtc\\utils\\Utils.java", "source_location": "L30"}, {"id": "utils_utils_utils_signalingstatestring", "label": ".signalingStateString()", "file_type": "code", "source_file": "C:\\MOYA\\flutter\\packages\\flutter_webrtc\\android\\src\\main\\java\\com\\cloudwebrtc\\webrtc\\utils\\Utils.java", "source_location": "L43"}, {"id": "utils_utils_utils_connectionstatestring", "label": ".connectionStateString()", "file_type": "code", "source_file": "C:\\MOYA\\flutter\\packages\\flutter_webrtc\\android\\src\\main\\java\\com\\cloudwebrtc\\webrtc\\utils\\Utils.java", "source_location": "L62"}], "edges": [{"source": "c_moya_flutter_packages_flutter_webrtc_android_src_main_java_com_cloudwebrtc_webrtc_utils_utils_java", "target": "nullable", "relation": "imports", "confidence": "EXTRACTED", "source_file": "C:\\MOYA\\flutter\\packages\\flutter_webrtc\\android\\src\\main\\java\\com\\cloudwebrtc\\webrtc\\utils\\Utils.java", "source_location": "L3", "weight": 1.0}, {"source": "c_moya_flutter_packages_flutter_webrtc_android_src_main_java_com_cloudwebrtc_webrtc_utils_utils_java", "target": "peerconnection", "relation": "imports", "confidence": "EXTRACTED", "source_file": "C:\\MOYA\\flutter\\packages\\flutter_webrtc\\android\\src\\main\\java\\com\\cloudwebrtc\\webrtc\\utils\\Utils.java", "source_location": "L5", "weight": 1.0}, {"source": "c_moya_flutter_packages_flutter_webrtc_android_src_main_java_com_cloudwebrtc_webrtc_utils_utils_java", "target": "utils_utils_utils", "relation": "contains", "confidence": "EXTRACTED", "source_file": "C:\\MOYA\\flutter\\packages\\flutter_webrtc\\android\\src\\main\\java\\com\\cloudwebrtc\\webrtc\\utils\\Utils.java", "source_location": "L7", "weight": 1.0}, {"source": "utils_utils_utils", "target": "utils_utils_utils_iceconnectionstatestring", "relation": "method", "confidence": "EXTRACTED", "source_file": "C:\\MOYA\\flutter\\packages\\flutter_webrtc\\android\\src\\main\\java\\com\\cloudwebrtc\\webrtc\\utils\\Utils.java", "source_location": "L9", "weight": 1.0}, {"source": "utils_utils_utils", "target": "utils_utils_utils_icegatheringstatestring", "relation": "method", "confidence": "EXTRACTED", "source_file": "C:\\MOYA\\flutter\\packages\\flutter_webrtc\\android\\src\\main\\java\\com\\cloudwebrtc\\webrtc\\utils\\Utils.java", "source_location": "L30", "weight": 1.0}, {"source": "utils_utils_utils", "target": "utils_utils_utils_signalingstatestring", "relation": "method", "confidence": "EXTRACTED", "source_file": "C:\\MOYA\\flutter\\packages\\flutter_webrtc\\android\\src\\main\\java\\com\\cloudwebrtc\\webrtc\\utils\\Utils.java", "source_location": "L43", "weight": 1.0}, {"source": "utils_utils_utils", "target": "utils_utils_utils_connectionstatestring", "relation": "method", "confidence": "EXTRACTED", "source_file": "C:\\MOYA\\flutter\\packages\\flutter_webrtc\\android\\src\\main\\java\\com\\cloudwebrtc\\webrtc\\utils\\Utils.java", "source_location": "L62", "weight": 1.0}], "raw_calls": []}