{"nodes": [{"id": "c_moya_flutter_packages_flutter_webrtc_ios_classes_media_stream_interface_h", "label": "media_stream_interface.h", "file_type": "code", "source_file": "C:\\MOYA\\flutter\\packages\\flutter_webrtc\\ios\\Classes\\media_stream_interface.h", "source_location": "L1"}, {"id": "classes_media_stream_interface_webrtc", "label": "webrtc()", "file_type": "code", "source_file": "C:\\MOYA\\flutter\\packages\\flutter_webrtc\\ios\\Classes\\media_stream_interface.h", "source_location": "L23"}], "edges": [{"source": "c_moya_flutter_packages_flutter_webrtc_ios_classes_media_stream_interface_h", "target": "stddef", "relation": "imports", "confidence": "EXTRACTED", "source_file": "C:\\MOYA\\flutter\\packages\\flutter_webrtc\\ios\\Classes\\media_stream_interface.h", "source_location": "L17", "weight": 1.0}, {"source": "c_moya_flutter_packages_flutter_webrtc_ios_classes_media_stream_interface_h", "target": "string", "relation": "imports", "confidence": "EXTRACTED", "source_file": "C:\\MOYA\\flutter\\packages\\flutter_webrtc\\ios\\Classes\\media_stream_interface.h", "source_location": "L18", "weight": 1.0}, {"source": "c_moya_flutter_packages_flutter_webrtc_ios_classes_media_stream_interface_h", "target": "vector", "relation": "imports", "confidence": "EXTRACTED", "source_file": "C:\\MOYA\\flutter\\packages\\flutter_webrtc\\ios\\Classes\\media_stream_interface.h", "source_location": "L19", "weight": 1.0}, {"source": "c_moya_flutter_packages_flutter_webrtc_ios_classes_media_stream_interface_h", "target": "memory", "relation": "imports", "confidence": "EXTRACTED", "source_file": "C:\\MOYA\\flutter\\packages\\flutter_webrtc\\ios\\Classes\\media_stream_interface.h", "source_location": "L20", "weight": 1.0}, {"source": "c_moya_flutter_packages_flutter_webrtc_ios_classes_media_stream_interface_h", "target": "utility", "relation": "imports", "confidence": "EXTRACTED", "source_file": "C:\\MOYA\\flutter\\packages\\flutter_webrtc\\ios\\Classes\\media_stream_interface.h", "source_location": "L21", "weight": 1.0}, {"source": "c_moya_flutter_packages_flutter_webrtc_ios_classes_media_stream_interface_h", "target": "classes_media_stream_interface_webrtc", "relation": "contains", "confidence": "EXTRACTED", "source_file": "C:\\MOYA\\flutter\\packages\\flutter_webrtc\\ios\\Classes\\media_stream_interface.h", "source_location": "L23", "weight": 1.0}], "raw_calls": []}