{"nodes": [{"id": "c_moya_flutter_packages_flutter_webrtc_linux_flutter_include_flutter_basic_message_channel_h", "label": "basic_message_channel.h", "file_type": "code", "source_file": "C:\\MOYA\\flutter\\packages\\flutter_webrtc\\linux\\flutter\\include\\flutter\\basic_message_channel.h", "source_location": "L1"}, {"id": "flutter_basic_message_channel_flutter", "label": "flutter()", "file_type": "code", "source_file": "C:\\MOYA\\flutter\\packages\\flutter_webrtc\\linux\\flutter\\include\\flutter\\basic_message_channel.h", "source_location": "L14"}], "edges": [{"source": "c_moya_flutter_packages_flutter_webrtc_linux_flutter_include_flutter_basic_message_channel_h", "target": "iostream", "relation": "imports", "confidence": "EXTRACTED", "source_file": "C:\\MOYA\\flutter\\packages\\flutter_webrtc\\linux\\flutter\\include\\flutter\\basic_message_channel.h", "source_location": "L8", "weight": 1.0}, {"source": "c_moya_flutter_packages_flutter_webrtc_linux_flutter_include_flutter_basic_message_channel_h", "target": "string", "relation": "imports", "confidence": "EXTRACTED", "source_file": "C:\\MOYA\\flutter\\packages\\flutter_webrtc\\linux\\flutter\\include\\flutter\\basic_message_channel.h", "source_location": "L9", "weight": 1.0}, {"source": "c_moya_flutter_packages_flutter_webrtc_linux_flutter_include_flutter_basic_message_channel_h", "target": "binary_messenger", "relation": "imports", "confidence": "EXTRACTED", "source_file": "C:\\MOYA\\flutter\\packages\\flutter_webrtc\\linux\\flutter\\include\\flutter\\basic_message_channel.h", "source_location": "L11", "weight": 1.0}, {"source": "c_moya_flutter_packages_flutter_webrtc_linux_flutter_include_flutter_basic_message_channel_h", "target": "message_codec", "relation": "imports", "confidence": "EXTRACTED", "source_file": "C:\\MOYA\\flutter\\packages\\flutter_webrtc\\linux\\flutter\\include\\flutter\\basic_message_channel.h", "source_location": "L12", "weight": 1.0}, {"source": "c_moya_flutter_packages_flutter_webrtc_linux_flutter_include_flutter_basic_message_channel_h", "target": "flutter_basic_message_channel_flutter", "relation": "contains", "confidence": "EXTRACTED", "source_file": "C:\\MOYA\\flutter\\packages\\flutter_webrtc\\linux\\flutter\\include\\flutter\\basic_message_channel.h", "source_location": "L14", "weight": 1.0}], "raw_calls": [{"caller_nid": "flutter_basic_message_channel_flutter", "callee": "void", "source_file": "C:\\MOYA\\flutter\\packages\\flutter_webrtc\\linux\\flutter\\include\\flutter\\basic_message_channel.h", "source_location": "L22"}, {"caller_nid": "flutter_basic_message_channel_flutter", "callee": "void", "source_file": "C:\\MOYA\\flutter\\packages\\flutter_webrtc\\linux\\flutter\\include\\flutter\\basic_message_channel.h", "source_location": "L30"}, {"caller_nid": "flutter_basic_message_channel_flutter", "callee": "BasicMessageChannel", "source_file": "C:\\MOYA\\flutter\\packages\\flutter_webrtc\\linux\\flutter\\include\\flutter\\basic_message_channel.h", "source_location": "L39"}, {"caller_nid": "flutter_basic_message_channel_flutter", "callee": "messenger_", "source_file": "C:\\MOYA\\flutter\\packages\\flutter_webrtc\\linux\\flutter\\include\\flutter\\basic_message_channel.h", "source_location": "L42"}, {"caller_nid": "flutter_basic_message_channel_flutter", "callee": "name_", "source_file": "C:\\MOYA\\flutter\\packages\\flutter_webrtc\\linux\\flutter\\include\\flutter\\basic_message_channel.h", "source_location": "L42"}, {"caller_nid": "flutter_basic_message_channel_flutter", "callee": "codec_", "source_file": "C:\\MOYA\\flutter\\packages\\flutter_webrtc\\linux\\flutter\\include\\flutter\\basic_message_channel.h", "source_location": "L42"}, {"caller_nid": "flutter_basic_message_channel_flutter", "callee": "BasicMessageChannel", "source_file": "C:\\MOYA\\flutter\\packages\\flutter_webrtc\\linux\\flutter\\include\\flutter\\basic_message_channel.h", "source_location": "L44"}, {"caller_nid": "flutter_basic_message_channel_flutter", "callee": "SetMessageHandler", "source_file": "C:\\MOYA\\flutter\\packages\\flutter_webrtc\\linux\\flutter\\include\\flutter\\basic_message_channel.h", "source_location": "L99"}, {"caller_nid": "flutter_basic_message_channel_flutter", "callee": "move", "source_file": "C:\\MOYA\\flutter\\packages\\flutter_webrtc\\linux\\flutter\\include\\flutter\\basic_message_channel.h", "source_location": "L99"}]}